seasonal/__init__.py
seasonal/__main__.py
seasonal/application.py
seasonal/periodogram.py
seasonal/seasonal.py
seasonal/sequences.py
seasonal/trend.py
seasonal/version.py
seasonal/data/airPassengers.csv
seasonal/data/beer.csv
seasonal-0.3.0.dist-info/DESCRIPTION.rst
seasonal-0.3.0.dist-info/METADATA
seasonal-0.3.0.dist-info/RECORD
seasonal-0.3.0.dist-info/WHEEL
seasonal-0.3.0.dist-info/entry_points.txt
seasonal-0.3.0.dist-info/metadata.json
seasonal-0.3.0.dist-info/top_level.txt
