Metadata-Version: 2.0
Name: seasonal
Version: 0.3.0
Summary: Estimate trend and seasonal effects in a timeseries
Home-page: https://github.com/welch/seasonal
Author: Will Welch
Author-email: github@quietplease.com
License: MIT
Keywords: timeseries,seasonality,seasonal adjustment,detrend,robust estimation,theil-sen,Holt-Winters
Platform: UNKNOWN
Classifier: Development Status :: 4 - Beta
Classifier: License :: OSI Approved :: MIT License
Classifier: Programming Language :: Python :: 2.7
Classifier: Programming Language :: Python :: 3
Classifier: Topic :: Scientific/Engineering
Requires-Dist: numpy
Requires-Dist: scipy
Provides-Extra: CSV
Requires-Dist: pandas; extra == 'CSV'
Provides-Extra: PLOT
Requires-Dist: matplotlib; extra == 'PLOT'
